LICENSE
wifipass/__init__.py
wifipass/__main__.py
wifipass-0.0.5.dist-info/entry_points.txt
wifipass-0.0.5.dist-info/LICENSE
wifipass-0.0.5.dist-info/WHEEL
wifipass-0.0.5.dist-info/METADATA
wifipass-0.0.5.dist-info/RECORD
